findout/__init__.py
findout/__main__.py
findout/_utils/__init__.py
findout/_utils/_funcs.py
findout/domains/__init__.py
findout/domains/sensitive_level.py
findout/findout.py
findout/search_tool.py
findout_in_comment-0.1.1.dist-info/entry_points.txt
findout_in_comment-0.1.1.dist-info/LICENSE
findout_in_comment-0.1.1.dist-info/WHEEL
findout_in_comment-0.1.1.dist-info/METADATA
findout_in_comment-0.1.1.dist-info/RECORD
