Metadata-Version: 2.1
Name: findout-in-comment
Version: 0.1.1
Summary: A pre-attack hacker tool to find out sensitives comments in HTML
Home-page: https://github.com/PabloEmidio/Findout-in-Comment
License: MIT
Author: Pablo Emidio
Author-email: p.emidiodev@gmail.com
Requires-Python: >=3.10,<4.0
Classifier: License :: OSI Approved :: MIT License
Classifier: Programming Language :: Python :: 3
Classifier: Programming Language :: Python :: 3.10
Classifier: Programming Language :: Python :: 3.11
Requires-Dist: parsel (>=1.6.0,<1.7.0)
Requires-Dist: requests (>=2.25.1,<2.26.0)
Project-URL: Repository, https://github.com/PabloEmidio/Findout-in-Comment
